gwmemory/__init__.py
gwmemory/_version.py
gwmemory/angles.py
gwmemory/gwmemory.py
gwmemory/harmonics.py
gwmemory/qnms.py
gwmemory/utils.py
gwmemory/waveforms/__init__.py
gwmemory/waveforms/approximant.py
gwmemory/waveforms/base.py
gwmemory/waveforms/mwm.py
gwmemory/waveforms/nr.py
gwmemory/waveforms/surrogate.py
gwmemory-1.1.0.dist-info/LICENSE
gwmemory-1.1.0.dist-info/METADATA
gwmemory-1.1.0.dist-info/WHEEL
gwmemory-1.1.0.dist-info/top_level.txt
gwmemory-1.1.0.dist-info/RECORD
