Metadata-Version: 2.1
Name: gwmemory
Version: 1.1.0
Summary: Calculate the gravitational-wave memory for arbitrary time series
Author-email: Colm Talbot <colm.talbot@ligo.org>
Classifier: License :: OSI Approved :: MIT License
Classifier: Operating System :: OS Independent
Requires-Python: >=3.8
License-File: LICENSE
Requires-Dist: numpy
Requires-Dist: scipy
Requires-Dist: sympy
Provides-Extra: dev
Requires-Dist: numba ; extra == 'dev'
